swe/__init__.py
swe/__main__.py
swe/cli.py
swe/common.py
swe/interactive.py
swe/sounds.py
swe/style.tcss
swe/textual_autocomplete/__init__.py
swe/textual_autocomplete/_autocomplete.py
swe/textual_autocomplete/_path_autocomplete.py
swe/textual_autocomplete/fuzzy_search.py
swe/textual_autocomplete/py.typed
swe-0.5.5.dist-info/METADATA
swe-0.5.5.dist-info/WHEEL
swe-0.5.5.dist-info/entry_points.txt
swe-0.5.5.dist-info/licenses/LICENSE
swe-0.5.5.dist-info/RECORD
