Metadata-Version: 2.4
Name: swe
Version: 0.5.5
Summary: Command line interface for Folkets lexikon, the Swedish-English dictionary
Project-URL: Homepage, https://github.com/bjesus/swe
Author-email: Yo'av Moshe <swe@yoavmoshe.com>
License-Expression: MIT
License-File: LICENSE
Requires-Python: >=3.10
Requires-Dist: editdistance>=0.8.1
Requires-Dist: lxml==5.2.2
Requires-Dist: markdownify>=0.12.1
Requires-Dist: mwclient>=0.10.1
Requires-Dist: requests>=2.32.3
Requires-Dist: textual==3.6.0
Requires-Dist: toml>=0.10.2
Requires-Dist: xdg-base-dirs>=6.0.2
